bit_field/__init__.py
bit_field/admin.py
bit_field/apps.py
bit_field/key.py
bit_field/models.py
bit_field/tests.py
bit_field/views.py
django_bitcoin_field-0.3.dist-info/LICENSE
django_bitcoin_field-0.3.dist-info/METADATA
django_bitcoin_field-0.3.dist-info/WHEEL
django_bitcoin_field-0.3.dist-info/top_level.txt
django_bitcoin_field-0.3.dist-info/RECORD
